kconfstyle/__init__.py
kconfstyle/__main__.py
kconfstyle-0.2.4.dist-info/WHEEL
kconfstyle-0.2.4.dist-info/entry_points.txt
kconfstyle-0.2.4.dist-info/METADATA
kconfstyle-0.2.4.dist-info/RECORD
