Metadata-Version: 2.4
Name: kconfstyle
Version: 0.2.4
Summary: Simple formatter for Kconfig files
License-Expression: MIT
Requires-Python: >=3.10
Project-URL: Homepage, https://github.com/noahp/kconfstyle
Project-URL: Issues, https://github.com/noahp/kconfstyle/issues
Project-URL: Repository, https://github.com/noahp/kconfstyle
